pyexcel_ods/__init__.py
pyexcel_ods/odsr.py
pyexcel_ods/odsw.py
pyexcel_ods-0.5.6.dist-info/LICENSE
pyexcel_ods-0.5.6.dist-info/METADATA
pyexcel_ods-0.5.6.dist-info/WHEEL
pyexcel_ods-0.5.6.dist-info/top_level.txt
pyexcel_ods-0.5.6.dist-info/RECORD
